{"nodes": [{"id": "rust_gil_release_pattern_pyo3_0_27", "label": "GIL Release Pattern for PyO3 0.27", "file_type": "document", "source_file": "rust/gil_release_pattern_pyo3_0.27.md", "source_location": null, "source_url": null, "captured_at": null, "author": null, "contributor": null}], "edges": [{"source": "rust_gil_release_pattern_pyo3_0_27", "target": "rust_pyo3_0_27_migration", "relation": "references", "confidence": "EXTRACTED", "confidence_score": 1.0, "source_file": "rust/gil_release_pattern_pyo3_0.27.md", "source_location": null, "weight": 1.0}], "hyperedges": []}