{"nodes": [{"id": "d_repos_classic_fallout4_tools_test_triple_gate_failure_py", "label": "test_triple_gate_failure.py", "file_type": "code", "source_file": "tools/test_triple_gate_failure.py", "source_location": "L1"}, {"id": "tools_test_triple_gate_failure_run_gate", "label": "run_gate()", "file_type": "code", "source_file": "tools/test_triple_gate_failure.py", "source_location": "L59"}, {"id": "path", "label": "Path", "file_type": "code", "source_file": "tools/test_triple_gate_failure.py", "source_location": "L59"}, {"id": "tools_test_triple_gate_failure_run_preflight", "label": "run_preflight()", "file_type": "code", "source_file": "tools/test_triple_gate_failure.py", "source_location": "L82"}, {"id": "tools_test_triple_gate_failure_inject_canaries", "label": "inject_canaries()", "file_type": "code", "source_file": "tools/test_triple_gate_failure.py", "source_location": "L107"}, {"id": "tools_test_triple_gate_failure_restore_files", "label": "restore_files()", "file_type": "code", "source_file": "tools/test_triple_gate_failure.py", "source_location": "L134"}, {"id": "tools_test_triple_gate_failure_main", "label": "main()", "file_type": "code", "source_file": "tools/test_triple_gate_failure.py", "source_location": "L145"}, {"id": "tools_test_triple_gate_failure_rationale_65", "label": "Run a single parity gate script and return (returncode, stdout, stderr).", "file_type": "rationale", "source_file": "tools/test_triple_gate_failure.py", "source_location": "L65"}, {"id": "tools_test_triple_gate_failure_rationale_86", "label": "Run all three gates and assert they all return 0 (clean baseline).      Return", "file_type": "rationale", "source_file": "tools/test_triple_gate_failure.py", "source_location": "L86"}, {"id": "tools_test_triple_gate_failure_rationale_113", "label": "Inject canary markers into both target files.", "file_type": "rationale", "source_file": "tools/test_triple_gate_failure.py", "source_location": "L113"}, {"id": "tools_test_triple_gate_failure_rationale_140", "label": "Restore both files to their original content.", "file_type": "rationale", "source_file": "tools/test_triple_gate_failure.py", "source_location": "L140"}], "edges": [{"source": "d_repos_classic_fallout4_tools_test_triple_gate_failure_py", "target": "argparse", "relation": "imports", "context": "import", "confidence": "EXTRACTED", "source_file": "tools/test_triple_gate_failure.py", "source_location": "L33", "weight": 1.0}, {"source": "d_repos_classic_fallout4_tools_test_triple_gate_failure_py", "target": "subprocess", "relation": "imports", "context": "import", "confidence": "EXTRACTED", "source_file": "tools/test_triple_gate_failure.py", "source_location": "L34", "weight": 1.0}, {"source": "d_repos_classic_fallout4_tools_test_triple_gate_failure_py", "target": "sys", "relation": "imports", "context": "import", "confidence": "EXTRACTED", "source_file": "tools/test_triple_gate_failure.py", "source_location": "L35", "weight": 1.0}, {"source": "d_repos_classic_fallout4_tools_test_triple_gate_failure_py", "target": "pathlib", "relation": "imports_from", "context": "import", "confidence": "EXTRACTED", "source_file": "tools/test_triple_gate_failure.py", "source_location": "L36", "weight": 1.0}, {"source": "d_repos_classic_fallout4_tools_test_triple_gate_failure_py", "target": "tools_test_triple_gate_failure_run_gate", "relation": "contains", "confidence": "EXTRACTED", "source_file": "tools/test_triple_gate_failure.py", "source_location": "L59", "weight": 1.0}, {"source": "tools_test_triple_gate_failure_run_gate", "target": "path", "relation": "references", "context": "parameter_type", "confidence": "EXTRACTED", "source_file": "tools/test_triple_gate_failure.py", "source_location": "L59", "weight": 1.0}, {"source": "tools_test_triple_gate_failure_run_gate", "target": "path", "relation": "references", "context": "parameter_type", "confidence": "EXTRACTED", "source_file": "tools/test_triple_gate_failure.py", "source_location": "L59", "weight": 1.0}, {"source": "d_repos_classic_fallout4_tools_test_triple_gate_failure_py", "target": "tools_test_triple_gate_failure_run_preflight", "relation": "contains", "confidence": "EXTRACTED", "source_file": "tools/test_triple_gate_failure.py", "source_location": "L82", "weight": 1.0}, {"source": "tools_test_triple_gate_failure_run_preflight", "target": "path", "relation": "references", "context": "parameter_type", "confidence": "EXTRACTED", "source_file": "tools/test_triple_gate_failure.py", "source_location": "L82", "weight": 1.0}, {"source": "d_repos_classic_fallout4_tools_test_triple_gate_failure_py", "target": "tools_test_triple_gate_failure_inject_canaries", "relation": "contains", "confidence": "EXTRACTED", "source_file": "tools/test_triple_gate_failure.py", "source_location": "L107", "weight": 1.0}, {"source": "tools_test_triple_gate_failure_inject_canaries", "target": "path", "relation": "references", "context": "parameter_type", "confidence": "EXTRACTED", "source_file": "tools/test_triple_gate_failure.py", "source_location": "L107", "weight": 1.0}, {"source": "tools_test_triple_gate_failure_inject_canaries", "target": "path", "relation": "references", "context": "parameter_type", "confidence": "EXTRACTED", "source_file": "tools/test_triple_gate_failure.py", "source_location": "L107", "weight": 1.0}, {"source": "d_repos_classic_fallout4_tools_test_triple_gate_failure_py", "target": "tools_test_triple_gate_failure_restore_files", "relation": "contains", "confidence": "EXTRACTED", "source_file": "tools/test_triple_gate_failure.py", "source_location": "L134", "weight": 1.0}, {"source": "tools_test_triple_gate_failure_restore_files", "target": "path", "relation": "references", "context": "parameter_type", "confidence": "EXTRACTED", "source_file": "tools/test_triple_gate_failure.py", "source_location": "L134", "weight": 1.0}, {"source": "tools_test_triple_gate_failure_restore_files", "target": "path", "relation": "references", "context": "parameter_type", "confidence": "EXTRACTED", "source_file": "tools/test_triple_gate_failure.py", "source_location": "L134", "weight": 1.0}, {"source": "d_repos_classic_fallout4_tools_test_triple_gate_failure_py", "target": "tools_test_triple_gate_failure_main", "relation": "contains", "confidence": "EXTRACTED", "source_file": "tools/test_triple_gate_failure.py", "source_location": "L145", "weight": 1.0}, {"source": "tools_test_triple_gate_failure_run_preflight", "target": "tools_test_triple_gate_failure_run_gate", "relation": "calls", "context": "call", "confidence": "EXTRACTED", "source_file": "tools/test_triple_gate_failure.py", "source_location": "L94", "weight": 1.0}, {"source": "tools_test_triple_gate_failure_main", "target": "path", "relation": "calls", "context": "call", "confidence": "EXTRACTED", "source_file": "tools/test_triple_gate_failure.py", "source_location": "L161", "weight": 1.0}, {"source": "tools_test_triple_gate_failure_main", "target": "tools_test_triple_gate_failure_run_preflight", "relation": "calls", "context": "call", "confidence": "EXTRACTED", "source_file": "tools/test_triple_gate_failure.py", "source_location": "L197", "weight": 1.0}, {"source": "tools_test_triple_gate_failure_main", "target": "tools_test_triple_gate_failure_inject_canaries", "relation": "calls", "context": "call", "confidence": "EXTRACTED", "source_file": "tools/test_triple_gate_failure.py", "source_location": "L211", "weight": 1.0}, {"source": "tools_test_triple_gate_failure_main", "target": "tools_test_triple_gate_failure_run_gate", "relation": "calls", "context": "call", "confidence": "EXTRACTED", "source_file": "tools/test_triple_gate_failure.py", "source_location": "L225", "weight": 1.0}, {"source": "tools_test_triple_gate_failure_main", "target": "tools_test_triple_gate_failure_restore_files", "relation": "calls", "context": "call", "confidence": "EXTRACTED", "source_file": "tools/test_triple_gate_failure.py", "source_location": "L237", "weight": 1.0}, {"source": "tools_test_triple_gate_failure_rationale_65", "target": "tools_test_triple_gate_failure_run_gate", "relation": "rationale_for", "confidence": "EXTRACTED", "source_file": "tools/test_triple_gate_failure.py", "source_location": "L65", "weight": 1.0}, {"source": "tools_test_triple_gate_failure_rationale_86", "target": "tools_test_triple_gate_failure_run_preflight", "relation": "rationale_for", "confidence": "EXTRACTED", "source_file": "tools/test_triple_gate_failure.py", "source_location": "L86", "weight": 1.0}, {"source": "tools_test_triple_gate_failure_rationale_113", "target": "tools_test_triple_gate_failure_inject_canaries", "relation": "rationale_for", "confidence": "EXTRACTED", "source_file": "tools/test_triple_gate_failure.py", "source_location": "L113", "weight": 1.0}, {"source": "tools_test_triple_gate_failure_rationale_140", "target": "tools_test_triple_gate_failure_restore_files", "relation": "rationale_for", "confidence": "EXTRACTED", "source_file": "tools/test_triple_gate_failure.py", "source_location": "L140", "weight": 1.0}], "raw_calls": [{"caller_nid": "tools_test_triple_gate_failure_run_gate", "callee": "run", "is_member_call": true, "source_file": "D:\\repos\\CLASSIC-Fallout4\\tools\\test_triple_gate_failure.py", "source_location": "L67", "receiver": null}, {"caller_nid": "tools_test_triple_gate_failure_inject_canaries", "callee": "write_text", "is_member_call": true, "source_file": "D:\\repos\\CLASSIC-Fallout4\\tools\\test_triple_gate_failure.py", "source_location": "L115", "receiver": null}, {"caller_nid": "tools_test_triple_gate_failure_inject_canaries", "callee": "find", "is_member_call": true, "source_file": "D:\\repos\\CLASSIC-Fallout4\\tools\\test_triple_gate_failure.py", "source_location": "L122", "receiver": null}, {"caller_nid": "tools_test_triple_gate_failure_inject_canaries", "callee": "RuntimeError", "is_member_call": false, "source_file": "D:\\repos\\CLASSIC-Fallout4\\tools\\test_triple_gate_failure.py", "source_location": "L124", "receiver": null}, {"caller_nid": "tools_test_triple_gate_failure_inject_canaries", "callee": "find", "is_member_call": true, "source_file": "D:\\repos\\CLASSIC-Fallout4\\tools\\test_triple_gate_failure.py", "source_location": "L125", "receiver": null}, {"caller_nid": "tools_test_triple_gate_failure_inject_canaries", "callee": "write_text", "is_member_call": true, "source_file": "D:\\repos\\CLASSIC-Fallout4\\tools\\test_triple_gate_failure.py", "source_location": "L131", "receiver": null}, {"caller_nid": "tools_test_triple_gate_failure_restore_files", "callee": "write_text", "is_member_call": true, "source_file": "D:\\repos\\CLASSIC-Fallout4\\tools\\test_triple_gate_failure.py", "source_location": "L141", "receiver": null}, {"caller_nid": "tools_test_triple_gate_failure_restore_files", "callee": "write_text", "is_member_call": true, "source_file": "D:\\repos\\CLASSIC-Fallout4\\tools\\test_triple_gate_failure.py", "source_location": "L142", "receiver": null}, {"caller_nid": "tools_test_triple_gate_failure_main", "callee": "ArgumentParser", "is_member_call": true, "source_file": "D:\\repos\\CLASSIC-Fallout4\\tools\\test_triple_gate_failure.py", "source_location": "L146", "receiver": null}, {"caller_nid": "tools_test_triple_gate_failure_main", "callee": "add_argument", "is_member_call": true, "source_file": "D:\\repos\\CLASSIC-Fallout4\\tools\\test_triple_gate_failure.py", "source_location": "L149", "receiver": null}, {"caller_nid": "tools_test_triple_gate_failure_main", "callee": "add_argument", "is_member_call": true, "source_file": "D:\\repos\\CLASSIC-Fallout4\\tools\\test_triple_gate_failure.py", "source_location": "L154", "receiver": null}, {"caller_nid": "tools_test_triple_gate_failure_main", "callee": "parse_args", "is_member_call": true, "source_file": "D:\\repos\\CLASSIC-Fallout4\\tools\\test_triple_gate_failure.py", "source_location": "L159", "receiver": null}, {"caller_nid": "tools_test_triple_gate_failure_main", "callee": "resolve", "is_member_call": true, "source_file": "D:\\repos\\CLASSIC-Fallout4\\tools\\test_triple_gate_failure.py", "source_location": "L161", "receiver": null}, {"caller_nid": "tools_test_triple_gate_failure_main", "callee": "exists", "is_member_call": true, "source_file": "D:\\repos\\CLASSIC-Fallout4\\tools\\test_triple_gate_failure.py", "source_location": "L168", "receiver": null}, {"caller_nid": "tools_test_triple_gate_failure_main", "callee": "read_text", "is_member_call": true, "source_file": "D:\\repos\\CLASSIC-Fallout4\\tools\\test_triple_gate_failure.py", "source_location": "L175", "receiver": null}, {"caller_nid": "tools_test_triple_gate_failure_main", "callee": "read_text", "is_member_call": true, "source_file": "D:\\repos\\CLASSIC-Fallout4\\tools\\test_triple_gate_failure.py", "source_location": "L176", "receiver": null}, {"caller_nid": "tools_test_triple_gate_failure_main", "callee": "values", "is_member_call": true, "source_file": "D:\\repos\\CLASSIC-Fallout4\\tools\\test_triple_gate_failure.py", "source_location": "L248", "receiver": null}, {"caller_nid": "tools_test_triple_gate_failure_main", "callee": "items", "is_member_call": true, "source_file": "D:\\repos\\CLASSIC-Fallout4\\tools\\test_triple_gate_failure.py", "source_location": "L254", "receiver": null}, {"caller_nid": "tools_test_triple_gate_failure_main", "callee": "join", "is_member_call": true, "source_file": "D:\\repos\\CLASSIC-Fallout4\\tools\\test_triple_gate_failure.py", "source_location": "L257", "receiver": null}]}