{"files": {"code": ["D:\\repos\\CLASSIC-Fallout4\\foundation\\classic-shared-core\\benches\\path_benchmarks.rs", "D:\\repos\\CLASSIC-Fallout4\\foundation\\classic-shared-core\\benches\\performance_benchmarks.rs", "D:\\repos\\CLASSIC-Fallout4\\foundation\\classic-shared-core\\benches\\string_benchmarks.rs", "D:\\repos\\CLASSIC-Fallout4\\foundation\\classic-shared-core\\src\\errors.rs", "D:\\repos\\CLASSIC-Fallout4\\foundation\\classic-shared-core\\src\\errors_tests.rs", "D:\\repos\\CLASSIC-Fallout4\\foundation\\classic-shared-core\\src\\game_id.rs", "D:\\repos\\CLASSIC-Fallout4\\foundation\\classic-shared-core\\src\\game_id_tests.rs", "D:\\repos\\CLASSIC-Fallout4\\foundation\\classic-shared-core\\src\\lib.rs", "D:\\repos\\CLASSIC-Fallout4\\foundation\\classic-shared-core\\src\\lib_tests.rs", "D:\\repos\\CLASSIC-Fallout4\\foundation\\classic-shared-core\\src\\path_core.rs", "D:\\repos\\CLASSIC-Fallout4\\foundation\\classic-shared-core\\src\\path_core_tests.rs", "D:\\repos\\CLASSIC-Fallout4\\foundation\\classic-shared-core\\src\\performance_core.rs", "D:\\repos\\CLASSIC-Fallout4\\foundation\\classic-shared-core\\src\\performance_core_tests.rs", "D:\\repos\\CLASSIC-Fallout4\\foundation\\classic-shared-core\\src\\strings_core.rs", "D:\\repos\\CLASSIC-Fallout4\\foundation\\classic-shared-core\\src\\strings_core_tests.rs", "D:\\repos\\CLASSIC-Fallout4\\foundation\\classic-shared-core\\tests\\test_path_lru.rs", "D:\\repos\\CLASSIC-Fallout4\\foundation\\classic-shared-core\\tests\\test_rolling_stats.rs", "D:\\repos\\CLASSIC-Fallout4\\foundation\\classic-shared-py\\src\\error_convert.rs", "D:\\repos\\CLASSIC-Fallout4\\foundation\\classic-shared-py\\src\\error_convert_tests.rs", "D:\\repos\\CLASSIC-Fallout4\\foundation\\classic-shared-py\\src\\exceptions.rs", "D:\\repos\\CLASSIC-Fallout4\\foundation\\classic-shared-py\\src\\exceptions_tests.rs", "D:\\repos\\CLASSIC-Fallout4\\foundation\\classic-shared-py\\src\\game_id.rs", "D:\\repos\\CLASSIC-Fallout4\\foundation\\classic-shared-py\\src\\indexmap_utils.rs", "D:\\repos\\CLASSIC-Fallout4\\foundation\\classic-shared-py\\src\\indexmap_utils_tests.rs", "D:\\repos\\CLASSIC-Fallout4\\foundation\\classic-shared-py\\src\\lib.rs", "D:\\repos\\CLASSIC-Fallout4\\foundation\\classic-shared-py\\src\\path.rs", "D:\\repos\\CLASSIC-Fallout4\\foundation\\classic-shared-py\\src\\path_py.rs", "D:\\repos\\CLASSIC-Fallout4\\foundation\\classic-shared-py\\src\\path_tests.rs", "D:\\repos\\CLASSIC-Fallout4\\foundation\\classic-shared-py\\src\\performance_py.rs", "D:\\repos\\CLASSIC-Fallout4\\foundation\\classic-shared-py\\src\\strings_py.rs"], "document": [], "paper": [], "image": [], "video": []}, "total_files": 30, "total_words": 16659, "needs_graph": false, "warning": "Corpus is ~16,659 words - fits in a single context window. You may not need a graph.", "skipped_sensitive": [], "graphifyignore_patterns": 102, "scan_root": "D:\\repos\\CLASSIC-Fallout4\\foundation"}