{"nodes": [{"id": "d_repos_classic_fallout4_business_logic_classic_settings_core_src_yaml_file_rs", "label": "yaml_file.rs", "file_type": "code", "source_file": "classic-settings-core/src/yaml_file.rs", "source_location": "L1"}, {"id": "src_yaml_file_yamlfile", "label": "YamlFile", "file_type": "code", "source_file": "classic-settings-core/src/yaml_file.rs", "source_location": "L5"}, {"id": "src_yaml_file_yamlfile_as_str", "label": ".as_str()", "file_type": "code", "source_file": "classic-settings-core/src/yaml_file.rs", "source_location": "L25"}, {"id": "src_yaml_file_yamlfile_description", "label": ".description()", "file_type": "code", "source_file": "classic-settings-core/src/yaml_file.rs", "source_location": "L39"}, {"id": "src_yaml_file_yamlfile_all", "label": ".all()", "file_type": "code", "source_file": "classic-settings-core/src/yaml_file.rs", "source_location": "L53"}, {"id": "self", "label": "Self", "file_type": "code", "source_file": "classic-settings-core/src/yaml_file.rs", "source_location": "L53"}, {"id": "display", "label": "Display", "file_type": "code", "source_file": "classic-settings-core/src/yaml_file.rs", "source_location": "L66"}, {"id": "src_yaml_file_yamlfile_fmt", "label": ".fmt()", "file_type": "code", "source_file": "classic-settings-core/src/yaml_file.rs", "source_location": "L67"}, {"id": "formatter", "label": "Formatter", "file_type": "code", "source_file": "classic-settings-core/src/yaml_file.rs", "source_location": "L67"}, {"id": "result", "label": "Result", "file_type": "code", "source_file": "classic-settings-core/src/yaml_file.rs", "source_location": "L67"}, {"id": "src_yaml_file_must_not_be_none", "label": "must_not_be_none()", "file_type": "code", "source_file": "classic-settings-core/src/yaml_file.rs", "source_location": "L83"}], "edges": [{"source": "d_repos_classic_fallout4_business_logic_classic_settings_core_src_yaml_file_rs", "target": "serde", "relation": "imports_from", "confidence": "EXTRACTED", "source_file": "classic-settings-core/src/yaml_file.rs", "source_location": "L1", "weight": 1.0, "context": "import"}, {"source": "d_repos_classic_fallout4_business_logic_classic_settings_core_src_yaml_file_rs", "target": "src_yaml_file_yamlfile", "relation": "contains", "confidence": "EXTRACTED", "source_file": "classic-settings-core/src/yaml_file.rs", "source_location": "L5", "weight": 1.0}, {"source": "src_yaml_file_yamlfile", "target": "src_yaml_file_yamlfile_as_str", "relation": "method", "confidence": "EXTRACTED", "source_file": "classic-settings-core/src/yaml_file.rs", "source_location": "L25", "weight": 1.0}, {"source": "src_yaml_file_yamlfile", "target": "src_yaml_file_yamlfile_description", "relation": "method", "confidence": "EXTRACTED", "source_file": "classic-settings-core/src/yaml_file.rs", "source_location": "L39", "weight": 1.0}, {"source": "src_yaml_file_yamlfile", "target": "src_yaml_file_yamlfile_all", "relation": "method", "confidence": "EXTRACTED", "source_file": "classic-settings-core/src/yaml_file.rs", "source_location": "L53", "weight": 1.0}, {"source": "src_yaml_file_yamlfile_all", "target": "self", "relation": "references", "confidence": "EXTRACTED", "source_file": "classic-settings-core/src/yaml_file.rs", "source_location": "L53", "weight": 1.0, "context": "return_type"}, {"source": "src_yaml_file_yamlfile", "target": "display", "relation": "implements", "confidence": "EXTRACTED", "source_file": "classic-settings-core/src/yaml_file.rs", "source_location": "L66", "weight": 1.0}, {"source": "src_yaml_file_yamlfile", "target": "src_yaml_file_yamlfile_fmt", "relation": "method", "confidence": "EXTRACTED", "source_file": "classic-settings-core/src/yaml_file.rs", "source_location": "L67", "weight": 1.0}, {"source": "src_yaml_file_yamlfile_fmt", "target": "formatter", "relation": "references", "confidence": "EXTRACTED", "source_file": "classic-settings-core/src/yaml_file.rs", "source_location": "L67", "weight": 1.0, "context": "parameter_type"}, {"source": "src_yaml_file_yamlfile_fmt", "target": "result", "relation": "references", "confidence": "EXTRACTED", "source_file": "classic-settings-core/src/yaml_file.rs", "source_location": "L67", "weight": 1.0, "context": "return_type"}, {"source": "d_repos_classic_fallout4_business_logic_classic_settings_core_src_yaml_file_rs", "target": "src_yaml_file_must_not_be_none", "relation": "contains", "confidence": "EXTRACTED", "source_file": "classic-settings-core/src/yaml_file.rs", "source_location": "L83", "weight": 1.0}], "raw_calls": []}